codeflare_sdk/__init__.py
codeflare_sdk/common/__init__.py
codeflare_sdk/common/kubernetes_cluster/__init__.py
codeflare_sdk/common/kubernetes_cluster/auth.py
codeflare_sdk/common/kubernetes_cluster/kube_api_helpers.py
codeflare_sdk/common/kubernetes_cluster/test_auth.py
codeflare_sdk/common/kueue/__init__.py
codeflare_sdk/common/kueue/kueue.py
codeflare_sdk/common/kueue/test_kueue.py
codeflare_sdk/common/utils/__init__.py
codeflare_sdk/common/utils/constants.py
codeflare_sdk/common/utils/demos.py
codeflare_sdk/common/utils/generate_cert.py
codeflare_sdk/common/utils/k8s_utils.py
codeflare_sdk/common/utils/test_demos.py
codeflare_sdk/common/utils/test_generate_cert.py
codeflare_sdk/common/utils/test_k8s_utils.py
codeflare_sdk/common/utils/test_utils.py
codeflare_sdk/common/utils/test_validation.py
codeflare_sdk/common/utils/unit_test_support.py
codeflare_sdk/common/utils/utils.py
codeflare_sdk/common/utils/validation.py
codeflare_sdk/common/widgets/__init__.py
codeflare_sdk/common/widgets/test_widgets.py
codeflare_sdk/common/widgets/widgets.py
codeflare_sdk/demo-notebooks/additional-demos/batch-inference/remote_offline_bi.ipynb
codeflare_sdk/demo-notebooks/additional-demos/batch-inference/requirements.txt
codeflare_sdk/demo-notebooks/additional-demos/batch-inference/simple_batch_inf.py
codeflare_sdk/demo-notebooks/additional-demos/hf_interactive.ipynb
codeflare_sdk/demo-notebooks/additional-demos/local_interactive.ipynb
codeflare_sdk/demo-notebooks/additional-demos/mnist.py
codeflare_sdk/demo-notebooks/additional-demos/ray_job_client.ipynb
codeflare_sdk/demo-notebooks/additional-demos/remote_ray_job_client.ipynb
codeflare_sdk/demo-notebooks/additional-demos/requirements.txt
codeflare_sdk/demo-notebooks/guided-demos/0_basic_ray.ipynb
codeflare_sdk/demo-notebooks/guided-demos/1_cluster_job_client.ipynb
codeflare_sdk/demo-notebooks/guided-demos/2_basic_interactive.ipynb
codeflare_sdk/demo-notebooks/guided-demos/3_widget_example.ipynb
codeflare_sdk-0.33.0.dist-info/LICENSE
codeflare_sdk-0.33.0.dist-info/METADATA
codeflare_sdk-0.33.0.dist-info/WHEEL
codeflare_sdk-0.33.0.dist-info/RECORD
