Metadata-Version: 2.1
Name: codeflare-sdk
Version: 0.33.0
Summary: Python SDK for codeflare client
Home-page: https://github.com/project-codeflare/codeflare-sdk
License: Apache-2.0
Keywords: codeflare,python,sdk,client,batch,scale
Author: Michael Clifford
Author-email: mcliffor@redhat.com
Requires-Python: >=3.11,<4.0
Classifier: License :: OSI Approved :: Apache Software License
Classifier: Programming Language :: Python :: 3
Classifier: Programming Language :: Python :: 3.11
Classifier: Programming Language :: Python :: 3.12
Requires-Dist: cryptography (==43.0.3)
Requires-Dist: executing (==1.2.0)
Requires-Dist: ipywidgets (==8.1.2)
Requires-Dist: kubernetes (>=27.2.0)
Requires-Dist: openshift-client (==1.0.18)
Requires-Dist: pydantic (>=2.10.6)
Requires-Dist: ray[data,default] (==2.52.1)
Requires-Dist: rich (>=12.5,<14.0)
Project-URL: Repository, https://github.com/project-codeflare/codeflare-sdk
